{
  "type": "FeatureCollection",
  "name": "yen-bai-tran-yen",
  "crs": {
    "type": "name",
    "properties": {
      "name": "urn:ogc:def:crs:OGC:1.3:CRS84"
    }
  },
  "features": [
    {
      "type": "Feature",
      "properties": {
        "tinh": "YênBai",
        "huyen": "TrấnYên",
        "xa_phuong": "BaoDáp"
      },
      "geometry": {
        "type": "MultiPolygon",
        "coordinates": [
          [
            [
              [
                104.7957,
                21.823
              ],
              [
                104.7891,
                21.8163
              ],
              [
                104.7871,
                21.8163
              ],
              [
                104.7867,
                21.8179
              ],
              [
                104.786,
                21.816
              ],
              [
                104.7818,
                21.8161
              ],
              [
                104.7839,
                21.8128
              ],
              [
                104.7793,
                21.8095
              ],
              [
                104.7781,
                21.8033
              ],
              [
                104.7727,
                21.804
              ],
              [
                104.7592,
                21.7988
              ],
              [
                104.7538,
                21.8013
              ],
              [
                104.7532,
                21.8094
              ],
              [
                104.756,
                21.8178
              ],
              [
                104.7471,
                21.8246
              ],
              [
                104.7411,
                21.8376
              ],
              [
                104.7435,
                21.84
              ],
              [
                104.7504,
                21.8407
              ],
              [
                104.761,
                21.8463
              ],
              [
                104.7645,
                21.8455
              ],
              [
                104.7623,
                21.8437
              ],
              [
                104.7633,
                21.8413
              ],
              [
                104.7685,
                21.8363
              ],
              [
                104.7738,
                21.8352
              ],
              [
                104.7768,
                21.8292
              ],
              [
                104.7893,
                21.8252
              ],
              [
                104.7911,
                21.8227
              ],
              [
                104.7957,
                21.823
              ]
            ]
          ]
        ]
      }
    },
    {
      "type": "Feature",
      "properties": {
        "tinh": "YênBai",
        "huyen": "TrấnYên",
        "xa_phuong": "BảoHưng"
      },
      "geometry": {
        "type": "MultiPolygon",
        "coordinates": [
          [
            [
              [
                104.9209,
                21.6618
              ],
              [
                104.9161,
                21.6564
              ],
              [
                104.9137,
                21.6564
              ],
              [
                104.9141,
                21.6539
              ],
              [
                104.9119,
                21.6519
              ],
              [
                104.9058,
                21.6513
              ],
              [
                104.8923,
                21.6623
              ],
              [
                104.8897,
                21.6612
              ],
              [
                104.8856,
                21.6632
              ],
              [
                104.8813,
                21.6607
              ],
              [
                104.8717,
                21.672
              ],
              [
                104.8738,
                21.6798
              ],
              [
                104.8721,
                21.6805
              ],
              [
                104.8776,
                21.6834
              ],
              [
                104.8817,
                21.6807
              ],
              [
                104.8927,
                21.6825
              ],
              [
                104.8945,
                21.684
              ],
              [
                104.8963,
                21.6814
              ],
              [
                104.9032,
                21.6784
              ],
              [
                104.9054,
                21.6733
              ],
              [
                104.9101,
                21.674
              ],
              [
                104.9144,
                21.6692
              ],
              [
                104.9141,
                21.6672
              ],
              [
                104.9209,
                21.6618
              ]
            ]
          ]
        ]
      }
    },
    {
      "type": "Feature",
      "properties": {
        "tinh": "YênBai",
        "huyen": "TrấnYên",
        "xa_phuong": "CổPhuc"
      },
      "geometry": {
        "type": "MultiPolygon",
        "coordinates": [
          [
            [
              [
                104.8184,
                21.7799
              ],
              [
                104.8202,
                21.7725
              ],
              [
                104.8232,
                21.772
              ],
              [
                104.826,
                21.7662
              ],
              [
                104.836,
                21.7558
              ],
              [
                104.8336,
                21.7537
              ],
              [
                104.8342,
                21.7498
              ],
              [
                104.8312,
                21.7462
              ],
              [
                104.8201,
                21.7563
              ],
              [
                104.8122,
                21.7586
              ],
              [
                104.8113,
                21.7629
              ],
              [
                104.8128,
                21.7677
              ],
              [
                104.8084,
                21.7728
              ],
              [
                104.8084,
                21.7753
              ],
              [
                104.8154,
                21.7758
              ],
              [
                104.8184,
                21.7799
              ]
            ]
          ]
        ]
      }
    },
    {
      "type": "Feature",
      "properties": {
        "tinh": "YênBai",
        "huyen": "TrấnYên",
        "xa_phuong": "CuờngThịnh"
      },
      "geometry": {
        "type": "MultiPolygon",
        "coordinates": [
          [
            [
              [
                104.8558,
                21.753
              ],
              [
                104.8615,
                21.7579
              ],
              [
                104.8649,
                21.7584
              ],
              [
                104.8661,
                21.7685
              ],
              [
                104.8681,
                21.7697
              ],
              [
                104.8684,
                21.7722
              ],
              [
                104.875,
                21.7767
              ],
              [
                104.8764,
                21.7825
              ],
              [
                104.8871,
                21.7862
              ],
              [
                104.8871,
                21.7838
              ],
              [
                104.891,
                21.7806
              ],
              [
                104.8914,
                21.7764
              ],
              [
                104.8951,
                21.7718
              ],
              [
                104.8948,
                21.7692
              ],
              [
                104.8996,
                21.7641
              ],
              [
                104.8976,
                21.7594
              ],
              [
                104.8953,
                21.7589
              ],
              [
                104.8939,
                21.7553
              ],
              [
                104.8909,
                21.7532
              ],
              [
                104.8902,
                21.7502
              ],
              [
                104.8926,
                21.7482
              ],
              [
                104.8862,
                21.7434
              ],
              [
                104.886,
                21.7372
              ],
              [
                104.8844,
                21.738
              ],
              [
                104.8821,
                21.7364
              ],
              [
                104.877,
                21.7391
              ],
              [
                104.8767,
                21.7347
              ],
              [
                104.8745,
                21.7356
              ],
              [
                104.8726,
                21.7326
              ],
              [
                104.8714,
                21.7342
              ],
              [
                104.8683,
                21.7323
              ],
              [
                104.8674,
                21.7297
              ],
              [
                104.8636,
                21.7282
              ],
              [
                104.8606,
                21.7294
              ],
              [
                104.8533,
                21.736
              ],
              [
                104.8587,
                21.7391
              ],
              [
                104.8596,
                21.7408
              ],
              [
                104.8582,
                21.7428
              ],
              [
                104.8603,
                21.7444
              ],
              [
                104.8587,
                21.7526
              ],
              [
                104.8558,
                21.753
              ]
            ]
          ]
        ]
      }
    },
    {
      "type": "Feature",
      "properties": {
        "tinh": "YênBai",
        "huyen": "TrấnYên",
        "xa_phuong": "DaoThịnh"
      },
      "geometry": {
        "type": "MultiPolygon",
        "coordinates": [
          [
            [
              [
                104.7781,
                21.8033
              ],
              [
                104.7793,
                21.8095
              ],
              [
                104.7839,
                21.8128
              ],
              [
                104.7818,
                21.8161
              ],
              [
                104.786,
                21.816
              ],
              [
                104.7867,
                21.8179
              ],
              [
                104.7871,
                21.8163
              ],
              [
                104.7891,
                21.8163
              ],
              [
                104.8005,
                21.8268
              ],
              [
                104.8033,
                21.8261
              ],
              [
                104.8136,
                21.832
              ],
              [
                104.8292,
                21.8309
              ],
              [
                104.8338,
                21.8283
              ],
              [
                104.8271,
                21.8214
              ],
              [
                104.8198,
                21.8186
              ],
              [
                104.819,
                21.8128
              ],
              [
                104.8121,
                21.8099
              ],
              [
                104.8126,
                21.8011
              ],
              [
                104.8065,
                21.7953
              ],
              [
                104.8056,
                21.7906
              ],
              [
                104.803,
                21.7872
              ],
              [
                104.7975,
                21.7922
              ],
              [
                104.7781,
                21.8033
              ]
            ]
          ]
        ]
      }
    },
    {
      "type": "Feature",
      "properties": {
        "tinh": "YênBai",
        "huyen": "TrấnYên",
        "xa_phuong": "HòaCuông"
      },
      "geometry": {
        "type": "MultiPolygon",
        "coordinates": [
          [
            [
              [
                104.8297,
                21.7637
              ],
              [
                104.826,
                21.7662
              ],
              [
                104.8232,
                21.772
              ],
              [
                104.8202,
                21.7725
              ],
              [
                104.8174,
                21.782
              ],
              [
                104.8206,
                21.7846
              ],
              [
                104.8246,
                21.7844
              ],
              [
                104.8284,
                21.7975
              ],
              [
                104.8287,
                21.8041
              ],
              [
                104.8351,
                21.8059
              ],
              [
                104.8368,
                21.8086
              ],
              [
                104.8352,
                21.8129
              ],
              [
                104.8391,
                21.8174
              ],
              [
                104.8389,
                21.8208
              ],
              [
                104.8426,
                21.8261
              ],
              [
                104.8484,
                21.8273
              ],
              [
                104.873,
                21.8151
              ],
              [
                104.878,
                21.8066
              ],
              [
                104.8649,
                21.7961
              ],
              [
                104.8577,
                21.7966
              ],
              [
                104.8506,
                21.7926
              ],
              [
                104.8494,
                21.7866
              ],
              [
                104.8386,
                21.7823
              ],
              [
                104.8366,
                21.7788
              ],
              [
                104.8368,
                21.7695
              ],
              [
                104.8343,
                21.7697
              ],
              [
                104.8297,
                21.7637
              ]
            ]
          ]
        ]
      }
    },
    {
      "type": "Feature",
      "properties": {
        "tinh": "YênBai",
        "huyen": "TrấnYên",
        "xa_phuong": "HồngCa"
      },
      "geometry": {
        "type": "MultiPolygon",
        "coordinates": [
          [
            [
              [
                104.7456,
                21.6088
              ],
              [
                104.7469,
                21.6061
              ],
              [
                104.7458,
                21.5989
              ],
              [
                104.7481,
                21.5969
              ],
              [
                104.7482,
                21.5874
              ],
              [
                104.7445,
                21.5826
              ],
              [
                104.7446,
                21.5743
              ],
              [
                104.7394,
                21.5726
              ],
              [
                104.7432,
                21.5687
              ],
              [
                104.7435,
                21.5617
              ],
              [
                104.7388,
                21.556
              ],
              [
                104.7395,
                21.5493
              ],
              [
                104.7318,
                21.5461
              ],
              [
                104.7284,
                21.5424
              ],
              [
                104.7293,
                21.5375
              ],
              [
                104.7263,
                21.5314
              ],
              [
                104.7207,
                21.5325
              ],
              [
                104.717,
                21.5359
              ],
              [
                104.7091,
                21.5385
              ],
              [
                104.7044,
                21.5433
              ],
              [
                104.6916,
                21.5503
              ],
              [
                104.6876,
                21.5674
              ],
              [
                104.6835,
                21.568
              ],
              [
                104.6819,
                21.5708
              ],
              [
                104.6765,
                21.5732
              ],
              [
                104.6724,
                21.5726
              ],
              [
                104.6685,
                21.5748
              ],
              [
                104.6639,
                21.5728
              ],
              [
                104.657,
                21.5758
              ],
              [
                104.6502,
                21.5864
              ],
              [
                104.6491,
                21.5908
              ],
              [
                104.6516,
                21.5929
              ],
              [
                104.6525,
                21.5971
              ],
              [
                104.6519,
                21.6143
              ],
              [
                104.6589,
                21.6168
              ],
              [
                104.6647,
                21.6225
              ],
              [
                104.6634,
                21.6291
              ],
              [
                104.6663,
                21.6327
              ],
              [
                104.6657,
                21.6396
              ],
              [
                104.6746,
                21.6445
              ],
              [
                104.6734,
                21.6485
              ],
              [
                104.6756,
                21.6504
              ],
              [
                104.6786,
                21.6616
              ],
              [
                104.6889,
                21.6648
              ],
              [
                104.6999,
                21.6583
              ],
              [
                104.7042,
                21.6523
              ],
              [
                104.7091,
                21.6526
              ],
              [
                104.7186,
                21.647
              ],
              [
                104.7189,
                21.6408
              ],
              [
                104.7332,
                21.6334
              ],
              [
                104.7383,
                21.6237
              ],
              [
                104.7407,
                21.6222
              ],
              [
                104.7405,
                21.6132
              ],
              [
                104.7456,
                21.6088
              ]
            ]
          ]
        ]
      }
    },
    {
      "type": "Feature",
      "properties": {
        "tinh": "YênBai",
        "huyen": "TrấnYên",
        "xa_phuong": "HưngKhánh"
      },
      "geometry": {
        "type": "MultiPolygon",
        "coordinates": [
          [
            [
              [
                104.7293,
                21.5375
              ],
              [
                104.7284,
                21.5424
              ],
              [
                104.7318,
                21.5461
              ],
              [
                104.7395,
                21.5493
              ],
              [
                104.7388,
                21.556
              ],
              [
                104.7435,
                21.5617
              ],
              [
                104.7432,
                21.5687
              ],
              [
                104.7394,
                21.5726
              ],
              [
                104.7446,
                21.5743
              ],
              [
                104.7445,
                21.5826
              ],
              [
                104.7482,
                21.5874
              ],
              [
                104.7481,
                21.5969
              ],
              [
                104.7458,
                21.5989
              ],
              [
                104.7469,
                21.6061
              ],
              [
                104.7456,
                21.6088
              ],
              [
                104.7488,
                21.611
              ],
              [
                104.7603,
                21.6117
              ],
              [
                104.7625,
                21.6145
              ],
              [
                104.7723,
                21.6148
              ],
              [
                104.7761,
                21.609
              ],
              [
                104.7764,
                21.6046
              ],
              [
                104.7742,
                21.6
              ],
              [
                104.7768,
                21.5956
              ],
              [
                104.7768,
                21.5873
              ],
              [
                104.7743,
                21.5769
              ],
              [
                104.7752,
                21.5752
              ],
              [
                104.7798,
                21.5743
              ],
              [
                104.7843,
                21.5652
              ],
              [
                104.7799,
                21.5611
              ],
              [
                104.7801,
                21.5574
              ],
              [
                104.7764,
                21.5534
              ],
              [
                104.7755,
                21.5498
              ],
              [
                104.7677,
                21.5411
              ],
              [
                104.7694,
                21.5351
              ],
              [
                104.766,
                21.5333
              ],
              [
                104.7618,
                21.5347
              ],
              [
                104.7421,
                21.531
              ],
              [
                104.7374,
                21.5368
              ],
              [
                104.7293,
                21.5375
              ]
            ]
          ]
        ]
      }
    },
    {
      "type": "Feature",
      "properties": {
        "tinh": "YênBai",
        "huyen": "TrấnYên",
        "xa_phuong": "HưngThịnh"
      },
      "geometry": {
        "type": "MultiPolygon",
        "coordinates": [
          [
            [
              [
                104.7843,
                21.5652
              ],
              [
                104.7798,
                21.5743
              ],
              [
                104.7752,
                21.5752
              ],
              [
                104.7743,
                21.5769
              ],
              [
                104.7768,
                21.5873
              ],
              [
                104.7768,
                21.5956
              ],
              [
                104.7742,
                21.6
              ],
              [
                104.7764,
                21.6046
              ],
              [
                104.7761,
                21.609
              ],
              [
                104.7723,
                21.6148
              ],
              [
                104.7625,
                21.6145
              ],
              [
                104.7651,
                21.6177
              ],
              [
                104.7727,
                21.6196
              ],
              [
                104.7798,
                21.6266
              ],
              [
                104.7869,
                21.6258
              ],
              [
                104.7932,
                21.6306
              ],
              [
                104.7973,
                21.6303
              ],
              [
                104.8051,
                21.6281
              ],
              [
                104.8091,
                21.6249
              ],
              [
                104.8137,
                21.6077
              ],
              [
                104.8129,
                21.6001
              ],
              [
                104.8085,
                21.5955
              ],
              [
                104.813,
                21.5912
              ],
              [
                104.8136,
                21.5834
              ],
              [
                104.8102,
                21.5798
              ],
              [
                104.809,
                21.5753
              ],
              [
                104.804,
                21.574
              ],
              [
                104.7967,
                21.5635
              ],
              [
                104.7936,
                21.5665
              ],
              [
                104.7843,
                21.5652
              ]
            ]
          ]
        ]
      }
    },
    {
      "type": "Feature",
      "properties": {
        "tinh": "YênBai",
        "huyen": "TrấnYên",
        "xa_phuong": "KiênThành"
      },
      "geometry": {
        "type": "MultiPolygon",
        "coordinates": [
          [
            [
              [
                104.7186,
                21.647
              ],
              [
                104.7091,
                21.6526
              ],
              [
                104.7042,
                21.6523
              ],
              [
                104.6999,
                21.6583
              ],
              [
                104.6939,
                21.6626
              ],
              [
                104.6955,
                21.6659
              ],
              [
                104.6959,
                21.6804
              ],
              [
                104.6897,
                21.689
              ],
              [
                104.6888,
                21.7051
              ],
              [
                104.6864,
                21.7099
              ],
              [
                104.6923,
                21.717
              ],
              [
                104.6913,
                21.7249
              ],
              [
                104.6967,
                21.7281
              ],
              [
                104.7109,
                21.7288
              ],
              [
                104.7182,
                21.7315
              ],
              [
                104.7188,
                21.7334
              ],
              [
                104.7125,
                21.7483
              ],
              [
                104.7178,
                21.7577
              ],
              [
                104.7225,
                21.7609
              ],
              [
                104.7231,
                21.7661
              ],
              [
                104.729,
                21.766
              ],
              [
                104.7322,
                21.7628
              ],
              [
                104.7366,
                21.7645
              ],
              [
                104.7337,
                21.7695
              ],
              [
                104.7339,
                21.7731
              ],
              [
                104.7423,
                21.7813
              ],
              [
                104.7451,
                21.7803
              ],
              [
                104.7483,
                21.7835
              ],
              [
                104.7521,
                21.7837
              ],
              [
                104.7599,
                21.7806
              ],
              [
                104.763,
                21.7743
              ],
              [
                104.7619,
                21.7719
              ],
              [
                104.7637,
                21.7699
              ],
              [
                104.768,
                21.7694
              ],
              [
                104.768,
                21.7678
              ],
              [
                104.77,
                21.7669
              ],
              [
                104.7715,
                21.7609
              ],
              [
                104.775,
                21.7595
              ],
              [
                104.7772,
                21.753
              ],
              [
                104.7695,
                21.7474
              ],
              [
                104.7711,
                21.7441
              ],
              [
                104.7702,
                21.7414
              ],
              [
                104.7661,
                21.7381
              ],
              [
                104.7707,
                21.7248
              ],
              [
                104.7669,
                21.7242
              ],
              [
                104.7662,
                21.7166
              ],
              [
                104.7611,
                21.718
              ],
              [
                104.7593,
                21.7169
              ],
              [
                104.7589,
                21.7103
              ],
              [
                104.756,
                21.7042
              ],
              [
                104.7552,
                21.6985
              ],
              [
                104.7595,
                21.6917
              ],
              [
                104.76,
                21.6819
              ],
              [
                104.7645,
                21.6768
              ],
              [
                104.7614,
                21.6725
              ],
              [
                104.7592,
                21.6637
              ],
              [
                104.7453,
                21.6579
              ],
              [
                104.7391,
                21.645
              ],
              [
                104.7258,
                21.6523
              ],
              [
                104.7186,
                21.647
              ]
            ]
          ]
        ]
      }
    },
    {
      "type": "Feature",
      "properties": {
        "tinh": "YênBai",
        "huyen": "TrấnYên",
        "xa_phuong": "LươngThịnh"
      },
      "geometry": {
        "type": "MultiPolygon",
        "coordinates": [
          [
            [
              [
                104.7456,
                21.6088
              ],
              [
                104.7405,
                21.6132
              ],
              [
                104.7407,
                21.6222
              ],
              [
                104.7383,
                21.6237
              ],
              [
                104.7332,
                21.6334
              ],
              [
                104.7189,
                21.6408
              ],
              [
                104.7186,
                21.647
              ],
              [
                104.7258,
                21.6523
              ],
              [
                104.7391,
                21.645
              ],
              [
                104.7453,
                21.6579
              ],
              [
                104.7592,
                21.6637
              ],
              [
                104.7614,
                21.6725
              ],
              [
                104.7645,
                21.6768
              ],
              [
                104.7671,
                21.675
              ],
              [
                104.7736,
                21.6764
              ],
              [
                104.78,
                21.6785
              ],
              [
                104.7815,
                21.6809
              ],
              [
                104.7875,
                21.6822
              ],
              [
                104.7896,
                21.6851
              ],
              [
                104.7895,
                21.6902
              ],
              [
                104.7918,
                21.6954
              ],
              [
                104.7991,
                21.6991
              ],
              [
                104.7945,
                21.7078
              ],
              [
                104.7962,
                21.7154
              ],
              [
                104.8,
                21.717
              ],
              [
                104.8071,
                21.7167
              ],
              [
                104.8125,
                21.7197
              ],
              [
                104.813,
                21.7216
              ],
              [
                104.8246,
                21.7036
              ],
              [
                104.8255,
                21.6988
              ],
              [
                104.8226,
                21.6935
              ],
              [
                104.8258,
                21.6887
              ],
              [
                104.8275,
                21.6808
              ],
              [
                104.8262,
                21.6738
              ],
              [
                104.8271,
                21.6703
              ],
              [
                104.829,
                21.6693
              ],
              [
                104.8248,
                21.6661
              ],
              [
                104.8261,
                21.6634
              ],
              [
                104.8234,
                21.6605
              ],
              [
                104.8267,
                21.6537
              ],
              [
                104.8276,
                21.635
              ],
              [
                104.8252,
                21.6336
              ],
              [
                104.8238,
                21.6292
              ],
              [
                104.8195,
                21.6264
              ],
              [
                104.8091,
                21.6249
              ],
              [
                104.8051,
                21.6281
              ],
              [
                104.7932,
                21.6306
              ],
              [
                104.7869,
                21.6258
              ],
              [
                104.7798,
                21.6266
              ],
              [
                104.7727,
                21.6196
              ],
              [
                104.7651,
                21.6177
              ],
              [
                104.7603,
                21.6117
              ],
              [
                104.7488,
                21.611
              ],
              [
                104.7456,
                21.6088
              ]
            ]
          ]
        ]
      }
    },
    {
      "type": "Feature",
      "properties": {
        "tinh": "YênBai",
        "huyen": "TrấnYên",
        "xa_phuong": "MinhQuán"
      },
      "geometry": {
        "type": "MultiPolygon",
        "coordinates": [
          [
            [
              [
                104.8358,
                21.7545
              ],
              [
                104.8297,
                21.7637
              ],
              [
                104.8343,
                21.7697
              ],
              [
                104.8368,
                21.7695
              ],
              [
                104.8366,
                21.7788
              ],
              [
                104.8386,
                21.7823
              ],
              [
                104.8494,
                21.7866
              ],
              [
                104.8506,
                21.7926
              ],
              [
                104.8577,
                21.7966
              ],
              [
                104.8649,
                21.7961
              ],
              [
                104.878,
                21.8066
              ],
              [
                104.8863,
                21.8
              ],
              [
                104.8913,
                21.7927
              ],
              [
                104.8871,
                21.7862
              ],
              [
                104.8764,
                21.7825
              ],
              [
                104.875,
                21.7767
              ],
              [
                104.8684,
                21.7722
              ],
              [
                104.8647,
                21.7651
              ],
              [
                104.8649,
                21.7584
              ],
              [
                104.8615,
                21.7579
              ],
              [
                104.854,
                21.7517
              ],
              [
                104.8501,
                21.7538
              ],
              [
                104.8477,
                21.7584
              ],
              [
                104.8417,
                21.7561
              ],
              [
                104.8393,
                21.7519
              ],
              [
                104.8374,
                21.7518
              ],
              [
                104.8358,
                21.7545
              ]
            ]
          ]
        ]
      }
    },
    {
      "type": "Feature",
      "properties": {
        "tinh": "YênBai",
        "huyen": "TrấnYên",
        "xa_phuong": "MinhQuân"
      },
      "geometry": {
        "type": "MultiPolygon",
        "coordinates": [
          [
            [
              [
                104.9378,
                21.6513
              ],
              [
                104.9371,
                21.6463
              ],
              [
                104.934,
                21.6426
              ],
              [
                104.9225,
                21.6405
              ],
              [
                104.9105,
                21.6346
              ],
              [
                104.9071,
                21.6312
              ],
              [
                104.9036,
                21.6222
              ],
              [
                104.9052,
                21.6093
              ],
              [
                104.9022,
                21.6105
              ],
              [
                104.8964,
                21.6083
              ],
              [
                104.891,
                21.6093
              ],
              [
                104.8881,
                21.6128
              ],
              [
                104.8904,
                21.6153
              ],
              [
                104.8911,
                21.621
              ],
              [
                104.8884,
                21.6232
              ],
              [
                104.8889,
                21.6259
              ],
              [
                104.8845,
                21.6286
              ],
              [
                104.8841,
                21.6314
              ],
              [
                104.8824,
                21.6325
              ],
              [
                104.884,
                21.6357
              ],
              [
                104.883,
                21.6374
              ],
              [
                104.8765,
                21.6421
              ],
              [
                104.8744,
                21.653
              ],
              [
                104.8707,
                21.6605
              ],
              [
                104.8725,
                21.6598
              ],
              [
                104.8753,
                21.6624
              ],
              [
                104.8789,
                21.66
              ],
              [
                104.8826,
                21.6606
              ],
              [
                104.8856,
                21.6632
              ],
              [
                104.8897,
                21.6612
              ],
              [
                104.8923,
                21.6623
              ],
              [
                104.9058,
                21.6513
              ],
              [
                104.9119,
                21.6519
              ],
              [
                104.9141,
                21.6539
              ],
              [
                104.9137,
                21.6564
              ],
              [
                104.9161,
                21.6564
              ],
              [
                104.9209,
                21.6618
              ],
              [
                104.923,
                21.6592
              ],
              [
                104.9241,
                21.6602
              ],
              [
                104.9243,
                21.6586
              ],
              [
                104.9255,
                21.6596
              ],
              [
                104.9262,
                21.6566
              ],
              [
                104.9322,
                21.6585
              ],
              [
                104.9324,
                21.6567
              ],
              [
                104.9351,
                21.6584
              ],
              [
                104.9378,
                21.6513
              ]
            ]
          ]
        ]
      }
    },
    {
      "type": "Feature",
      "properties": {
        "tinh": "YênBai",
        "huyen": "TrấnYên",
        "xa_phuong": "MinhTiến"
      },
      "geometry": {
        "type": "MultiPolygon",
        "coordinates": [
          [
            [
              [
                104.8205,
                21.7096
              ],
              [
                104.8117,
                21.7238
              ],
              [
                104.8145,
                21.7299
              ],
              [
                104.8255,
                21.7321
              ],
              [
                104.8265,
                21.7375
              ],
              [
                104.8315,
                21.7404
              ],
              [
                104.8333,
                21.7394
              ],
              [
                104.8352,
                21.7422
              ],
              [
                104.8425,
                21.7334
              ],
              [
                104.8423,
                21.7274
              ],
              [
                104.8383,
                21.7196
              ],
              [
                104.8391,
                21.7159
              ],
              [
                104.8336,
                21.7111
              ],
              [
                104.8275,
                21.712
              ],
              [
                104.8205,
                21.7096
              ]
            ]
          ]
        ]
      }
    },
    {
      "type": "Feature",
      "properties": {
        "tinh": "YênBai",
        "huyen": "TrấnYên",
        "xa_phuong": "NgaQuán"
      },
      "geometry": {
        "type": "MultiPolygon",
        "coordinates": [
          [
            [
              [
                104.8312,
                21.7462
              ],
              [
                104.8342,
                21.7498
              ],
              [
                104.8336,
                21.7537
              ],
              [
                104.8358,
                21.7545
              ],
              [
                104.8374,
                21.7518
              ],
              [
                104.8393,
                21.7519
              ],
              [
                104.8417,
                21.7561
              ],
              [
                104.8477,
                21.7584
              ],
              [
                104.8501,
                21.7538
              ],
              [
                104.853,
                21.7518
              ],
              [
                104.8587,
                21.7526
              ],
              [
                104.8603,
                21.7444
              ],
              [
                104.8582,
                21.7428
              ],
              [
                104.8596,
                21.7408
              ],
              [
                104.8587,
                21.7391
              ],
              [
                104.8533,
                21.736
              ],
              [
                104.8522,
                21.7373
              ],
              [
                104.8488,
                21.7343
              ],
              [
                104.8448,
                21.7344
              ],
              [
                104.8439,
                21.7356
              ],
              [
                104.8419,
                21.7346
              ],
              [
                104.8312,
                21.7462
              ]
            ]
          ]
        ]
      }
    },
    {
      "type": "Feature",
      "properties": {
        "tinh": "YênBai",
        "huyen": "TrấnYên",
        "xa_phuong": "QuyMông"
      },
      "geometry": {
        "type": "MultiPolygon",
        "coordinates": [
          [
            [
              [
                104.7664,
                21.8006
              ],
              [
                104.7759,
                21.8043
              ],
              [
                104.7975,
                21.7922
              ],
              [
                104.803,
                21.7872
              ],
              [
                104.8032,
                21.7804
              ],
              [
                104.7958,
                21.7732
              ],
              [
                104.792,
                21.7639
              ],
              [
                104.7927,
                21.7576
              ],
              [
                104.7961,
                21.755
              ],
              [
                104.7948,
                21.7508
              ],
              [
                104.7959,
                21.7478
              ],
              [
                104.7941,
                21.7455
              ],
              [
                104.7962,
                21.7428
              ],
              [
                104.7953,
                21.7395
              ],
              [
                104.7922,
                21.7377
              ],
              [
                104.7883,
                21.737
              ],
              [
                104.7824,
                21.7419
              ],
              [
                104.7702,
                21.7414
              ],
              [
                104.7711,
                21.7441
              ],
              [
                104.7695,
                21.7474
              ],
              [
                104.7766,
                21.7519
              ],
              [
                104.7766,
                21.7565
              ],
              [
                104.775,
                21.7595
              ],
              [
                104.7715,
                21.7609
              ],
              [
                104.7712,
                21.765
              ],
              [
                104.768,
                21.7694
              ],
              [
                104.7637,
                21.7699
              ],
              [
                104.7619,
                21.7719
              ],
              [
                104.763,
                21.7743
              ],
              [
                104.7599,
                21.7806
              ],
              [
                104.7582,
                21.7808
              ],
              [
                104.7607,
                21.7818
              ],
              [
                104.7604,
                21.7841
              ],
              [
                104.7619,
                21.7852
              ],
              [
                104.7681,
                21.7854
              ],
              [
                104.7621,
                21.7892
              ],
              [
                104.7648,
                21.7913
              ],
              [
                104.7635,
                21.7961
              ],
              [
                104.7664,
                21.8006
              ]
            ]
          ]
        ]
      }
    },
    {
      "type": "Feature",
      "properties": {
        "tinh": "YênBai",
        "huyen": "TrấnYên",
        "xa_phuong": "TânDong"
      },
      "geometry": {
        "type": "MultiPolygon",
        "coordinates": [
          [
            [
              [
                104.7957,
                21.823
              ],
              [
                104.7911,
                21.8227
              ],
              [
                104.7893,
                21.8252
              ],
              [
                104.7768,
                21.8292
              ],
              [
                104.7738,
                21.8352
              ],
              [
                104.7685,
                21.8363
              ],
              [
                104.7623,
                21.8437
              ],
              [
                104.7692,
                21.8467
              ],
              [
                104.7713,
                21.8522
              ],
              [
                104.7742,
                21.8547
              ],
              [
                104.7759,
                21.8589
              ],
              [
                104.7751,
                21.8694
              ],
              [
                104.7811,
                21.8732
              ],
              [
                104.7841,
                21.8718
              ],
              [
                104.7867,
                21.8763
              ],
              [
                104.7956,
                21.8785
              ],
              [
                104.8037,
                21.875
              ],
              [
                104.8264,
                21.8559
              ],
              [
                104.8338,
                21.8283
              ],
              [
                104.8292,
                21.8309
              ],
              [
                104.8136,
                21.832
              ],
              [
                104.8033,
                21.8261
              ],
              [
                104.8005,
                21.8268
              ],
              [
                104.7957,
                21.823
              ]
            ]
          ]
        ]
      }
    },
    {
      "type": "Feature",
      "properties": {
        "tinh": "YênBai",
        "huyen": "TrấnYên",
        "xa_phuong": "VânHội"
      },
      "geometry": {
        "type": "MultiPolygon",
        "coordinates": [
          [
            [
              [
                104.8914,
                21.6016
              ],
              [
                104.8928,
                21.5912
              ],
              [
                104.8963,
                21.5871
              ],
              [
                104.8976,
                21.5813
              ],
              [
                104.8988,
                21.5652
              ],
              [
                104.8878,
                21.5577
              ],
              [
                104.8826,
                21.5588
              ],
              [
                104.8771,
                21.5558
              ],
              [
                104.872,
                21.5554
              ],
              [
                104.8704,
                21.5662
              ],
              [
                104.8672,
                21.5709
              ],
              [
                104.8695,
                21.5781
              ],
              [
                104.8653,
                21.5822
              ],
              [
                104.8632,
                21.589
              ],
              [
                104.8579,
                21.5943
              ],
              [
                104.8495,
                21.5967
              ],
              [
                104.8451,
                21.5937
              ],
              [
                104.8424,
                21.5953
              ],
              [
                104.8374,
                21.5952
              ],
              [
                104.8349,
                21.5929
              ],
              [
                104.8252,
                21.5937
              ],
              [
                104.8257,
                21.5973
              ],
              [
                104.8285,
                21.6011
              ],
              [
                104.8355,
                21.6008
              ],
              [
                104.8356,
                21.6037
              ],
              [
                104.8423,
                21.6057
              ],
              [
                104.8508,
                21.6045
              ],
              [
                104.8567,
                21.6087
              ],
              [
                104.8573,
                21.6053
              ],
              [
                104.863,
                21.6049
              ],
              [
                104.8687,
                21.5991
              ],
              [
                104.872,
                21.599
              ],
              [
                104.8736,
                21.5969
              ],
              [
                104.8797,
                21.5978
              ],
              [
                104.8812,
                21.6001
              ],
              [
                104.8878,
                21.6035
              ],
              [
                104.8914,
                21.6016
              ]
            ]
          ]
        ]
      }
    },
    {
      "type": "Feature",
      "properties": {
        "tinh": "YênBai",
        "huyen": "TrấnYên",
        "xa_phuong": "ViệtCuờng"
      },
      "geometry": {
        "type": "MultiPolygon",
        "coordinates": [
          [
            [
              [
                104.8881,
                21.6128
              ],
              [
                104.8887,
                21.6094
              ],
              [
                104.8936,
                21.6043
              ],
              [
                104.8914,
                21.6016
              ],
              [
                104.8878,
                21.6035
              ],
              [
                104.8777,
                21.5971
              ],
              [
                104.8736,
                21.5969
              ],
              [
                104.872,
                21.599
              ],
              [
                104.8687,
                21.5991
              ],
              [
                104.863,
                21.6049
              ],
              [
                104.8573,
                21.6053
              ],
              [
                104.8567,
                21.6087
              ],
              [
                104.8508,
                21.6045
              ],
              [
                104.8423,
                21.6057
              ],
              [
                104.8356,
                21.6037
              ],
              [
                104.8355,
                21.6008
              ],
              [
                104.8285,
                21.6011
              ],
              [
                104.8257,
                21.5973
              ],
              [
                104.8252,
                21.5937
              ],
              [
                104.8207,
                21.5917
              ],
              [
                104.8153,
                21.597
              ],
              [
                104.8085,
                21.5955
              ],
              [
                104.8129,
                21.6001
              ],
              [
                104.8137,
                21.6077
              ],
              [
                104.8091,
                21.6249
              ],
              [
                104.8212,
                21.6271
              ],
              [
                104.8276,
                21.635
              ],
              [
                104.8267,
                21.6537
              ],
              [
                104.8234,
                21.6605
              ],
              [
                104.8261,
                21.6634
              ],
              [
                104.8248,
                21.6661
              ],
              [
                104.829,
                21.6693
              ],
              [
                104.8346,
                21.667
              ],
              [
                104.8384,
                21.6692
              ],
              [
                104.8432,
                21.6679
              ],
              [
                104.8496,
                21.6693
              ],
              [
                104.8544,
                21.6666
              ],
              [
                104.8629,
                21.6677
              ],
              [
                104.8679,
                21.6643
              ],
              [
                104.8744,
                21.653
              ],
              [
                104.8765,
                21.6421
              ],
              [
                104.883,
                21.6374
              ],
              [
                104.884,
                21.6357
              ],
              [
                104.8824,
                21.6325
              ],
              [
                104.8841,
                21.6314
              ],
              [
                104.8845,
                21.6286
              ],
              [
                104.8889,
                21.6259
              ],
              [
                104.8884,
                21.6232
              ],
              [
                104.8911,
                21.621
              ],
              [
                104.8904,
                21.6153
              ],
              [
                104.8881,
                21.6128
              ]
            ]
          ]
        ]
      }
    },
    {
      "type": "Feature",
      "properties": {
        "tinh": "YênBai",
        "huyen": "TrấnYên",
        "xa_phuong": "ViệtHồng"
      },
      "geometry": {
        "type": "MultiPolygon",
        "coordinates": [
          [
            [
              [
                104.872,
                21.5554
              ],
              [
                104.8678,
                21.5487
              ],
              [
                104.8685,
                21.5421
              ],
              [
                104.8601,
                21.5319
              ],
              [
                104.8576,
                21.5332
              ],
              [
                104.8528,
                21.5326
              ],
              [
                104.8454,
                21.5367
              ],
              [
                104.8413,
                21.5434
              ],
              [
                104.8313,
                21.5466
              ],
              [
                104.827,
                21.5529
              ],
              [
                104.8186,
                21.5524
              ],
              [
                104.813,
                21.5569
              ],
              [
                104.8038,
                21.5561
              ],
              [
                104.7967,
                21.5635
              ],
              [
                104.804,
                21.574
              ],
              [
                104.809,
                21.5753
              ],
              [
                104.8102,
                21.5798
              ],
              [
                104.8136,
                21.5834
              ],
              [
                104.813,
                21.5912
              ],
              [
                104.8085,
                21.5955
              ],
              [
                104.8153,
                21.597
              ],
              [
                104.8207,
                21.5917
              ],
              [
                104.8252,
                21.5937
              ],
              [
                104.8349,
                21.5929
              ],
              [
                104.8374,
                21.5952
              ],
              [
                104.8424,
                21.5953
              ],
              [
                104.8451,
                21.5937
              ],
              [
                104.8495,
                21.5967
              ],
              [
                104.8579,
                21.5943
              ],
              [
                104.8632,
                21.589
              ],
              [
                104.8653,
                21.5822
              ],
              [
                104.8695,
                21.5781
              ],
              [
                104.8672,
                21.5709
              ],
              [
                104.8704,
                21.5662
              ],
              [
                104.872,
                21.5554
              ]
            ]
          ]
        ]
      }
    },
    {
      "type": "Feature",
      "properties": {
        "tinh": "YênBai",
        "huyen": "TrấnYên",
        "xa_phuong": "ViệtThành"
      },
      "geometry": {
        "type": "MultiPolygon",
        "coordinates": [
          [
            [
              [
                104.8184,
                21.7799
              ],
              [
                104.8154,
                21.7758
              ],
              [
                104.8084,
                21.7753
              ],
              [
                104.8084,
                21.7728
              ],
              [
                104.8128,
                21.7677
              ],
              [
                104.8113,
                21.7629
              ],
              [
                104.8122,
                21.7586
              ],
              [
                104.8008,
                21.7545
              ],
              [
                104.7961,
                21.755
              ],
              [
                104.7927,
                21.7576
              ],
              [
                104.792,
                21.7639
              ],
              [
                104.7958,
                21.7732
              ],
              [
                104.8032,
                21.7804
              ],
              [
                104.803,
                21.7872
              ],
              [
                104.8056,
                21.7906
              ],
              [
                104.8065,
                21.7953
              ],
              [
                104.8126,
                21.8011
              ],
              [
                104.8121,
                21.8099
              ],
              [
                104.819,
                21.8128
              ],
              [
                104.8198,
                21.8186
              ],
              [
                104.8271,
                21.8214
              ],
              [
                104.8338,
                21.8283
              ],
              [
                104.8371,
                21.8286
              ],
              [
                104.8426,
                21.8261
              ],
              [
                104.8389,
                21.8208
              ],
              [
                104.8391,
                21.8174
              ],
              [
                104.8352,
                21.8129
              ],
              [
                104.8368,
                21.8086
              ],
              [
                104.8351,
                21.8059
              ],
              [
                104.8287,
                21.8041
              ],
              [
                104.8284,
                21.7975
              ],
              [
                104.8246,
                21.7844
              ],
              [
                104.8179,
                21.7832
              ],
              [
                104.8184,
                21.7799
              ]
            ]
          ]
        ]
      }
    },
    {
      "type": "Feature",
      "properties": {
        "tinh": "YênBai",
        "huyen": "TrấnYên",
        "xa_phuong": "YCan"
      },
      "geometry": {
        "type": "MultiPolygon",
        "coordinates": [
          [
            [
              [
                104.8122,
                21.7586
              ],
              [
                104.8201,
                21.7563
              ],
              [
                104.8352,
                21.7422
              ],
              [
                104.8333,
                21.7394
              ],
              [
                104.8315,
                21.7404
              ],
              [
                104.8265,
                21.7375
              ],
              [
                104.8255,
                21.7321
              ],
              [
                104.8145,
                21.7299
              ],
              [
                104.8117,
                21.7238
              ],
              [
                104.8125,
                21.7197
              ],
              [
                104.8071,
                21.7167
              ],
              [
                104.8,
                21.717
              ],
              [
                104.7962,
                21.7154
              ],
              [
                104.7945,
                21.7078
              ],
              [
                104.7991,
                21.6991
              ],
              [
                104.7918,
                21.6954
              ],
              [
                104.7895,
                21.6902
              ],
              [
                104.7896,
                21.6851
              ],
              [
                104.7875,
                21.6822
              ],
              [
                104.7671,
                21.675
              ],
              [
                104.76,
                21.6819
              ],
              [
                104.7595,
                21.6917
              ],
              [
                104.7552,
                21.6985
              ],
              [
                104.7589,
                21.7103
              ],
              [
                104.7593,
                21.7169
              ],
              [
                104.7611,
                21.718
              ],
              [
                104.7662,
                21.7166
              ],
              [
                104.7669,
                21.7242
              ],
              [
                104.7707,
                21.7248
              ],
              [
                104.7661,
                21.7381
              ],
              [
                104.7702,
                21.7414
              ],
              [
                104.78,
                21.742
              ],
              [
                104.7824,
                21.7419
              ],
              [
                104.7883,
                21.737
              ],
              [
                104.7922,
                21.7377
              ],
              [
                104.7953,
                21.7395
              ],
              [
                104.7962,
                21.7428
              ],
              [
                104.7941,
                21.7455
              ],
              [
                104.7959,
                21.7478
              ],
              [
                104.7948,
                21.7508
              ],
              [
                104.7961,
                21.755
              ],
              [
                104.8008,
                21.7545
              ],
              [
                104.8122,
                21.7586
              ]
            ]
          ]
        ]
      }
    }
  ]
}